dbkrpy/__init__.py
dbkrpy/dbkrapiurl.py
dbkrpy/dbkrcategories.py
dbkrpy/dbkrgetbyid.py
dbkrpy/dbkrpage.py
dbkrpy/dbkrseach.py
dbkrpy/dbkrsort.py
dbkrpy/dbkrupdateguilds.py
dbkrpy/dbkrvote.py
test/__init__.py
test/test_requests.py
dbkrpy-0.5.2.dist-info/LICENSE
dbkrpy-0.5.2.dist-info/METADATA
dbkrpy-0.5.2.dist-info/WHEEL
dbkrpy-0.5.2.dist-info/top_level.txt
dbkrpy-0.5.2.dist-info/RECORD
