Metadata-Version: 2.1
Name: dbkrpy
Version: 0.5.2
Summary: DBKR Api wrapped with aiohttp
Home-page: https://github.com/SaidBySolo/DBKR-API-Python
Author: Ryu ju heon
Author-email: SaidBySolo@gmail.com
License: MIT
Platform: UNKNOWN
Classifier: Programming Language :: Python :: 3.8
Classifier: License :: OSI Approved :: MIT License
Classifier: Operating System :: OS Independent
Requires-Python: >=3.6
Requires-Dist: aiohttp[speedup]
